pymprpc/__init__.py
pymprpc/errors.py
pymprpc/status_codes.py
pymprpc/client/__init__.py
pymprpc/client/aio.py
pymprpc/client/sync.py
pymprpc/client/utils.py
pymprpc/mixins/__init__.py
pymprpc/mixins/encoder_decoder_mixin.py
pymprpc/server/__init__.py
pymprpc/server/log.py
pymprpc/server/protocol.py
pymprpc/server/server.py
pymprpc/server/utils.py
pymprpc-0.0.3.data/data/requirements/requirements.txt
pymprpc-0.0.3.data/data/requirements/requirements_dev.txt
pymprpc-0.0.3.data/data/requirements/requirements_test.txt
pymprpc-0.0.3.dist-info/DESCRIPTION.rst
pymprpc-0.0.3.dist-info/METADATA
pymprpc-0.0.3.dist-info/RECORD
pymprpc-0.0.3.dist-info/WHEEL
pymprpc-0.0.3.dist-info/metadata.json
pymprpc-0.0.3.dist-info/top_level.txt
