Metadata-Version: 2.0
Name: pymprpc
Version: 0.0.3
Summary: a rpc framework for message-pack rpc.
Home-page: https://github.com/Basic-Components/msgpack-rpc-protocol
Author: hsz
Author-email: hsz1273327@gmail.com
License: MIT
Keywords: rpc,server,tcp
Platform: UNKNOWN
Classifier: Development Status :: 3 - Alpha
Classifier: Intended Audience :: Developers
Classifier: License :: OSI Approved :: MIT License
Classifier: Programming Language :: Python :: 3.5
Classifier: Programming Language :: Python :: 3.6
Classifier: Topic :: Documentation :: Sphinx
Requires-Dist: msgpack
Provides-Extra: dev
Requires-Dist: wheel; extra == 'dev'
Provides-Extra: test
Requires-Dist: coverage; extra == 'test'
Requires-Dist: mypy; extra == 'test'
Requires-Dist: mypy-extensions; extra == 'test'
Requires-Dist: lxml; extra == 'test'
